cloudteam_servicebus/cloudteam_servicebus.py
cloudteam_servicebus-1.0.0.dist-info/LICENSE
cloudteam_servicebus-1.0.0.dist-info/METADATA
cloudteam_servicebus-1.0.0.dist-info/WHEEL
cloudteam_servicebus-1.0.0.dist-info/top_level.txt
cloudteam_servicebus-1.0.0.dist-info/RECORD
