Metadata-Version: 2.1
Name: cloudteam_servicebus
Version: 1.0.0
Summary: A service bus module for cloudteam
Author-email: "CloudTeam.AI" <devops@cloudteam.ai>
Classifier: Programming Language :: Python :: 3
Classifier: License :: OSI Approved :: MIT License
Classifier: Operating System :: OS Independent
Requires-Python: >=3.8
License-File: LICENSE
